[
    {
        "Id": "232924f5-81e1-49ae-a7ec-1aa48d4f086c",
        "FirstName": "John",
        "LastName": "Will",
        "Email": "john@owner.com",
        "Address": "456 Business Blvd",
        "DateOfBirth": "1980-05-20"
    },
    {
        "Id": "3365e4ed-f8e1-49dc-8342-b3dc85426213",
        "FirstName": "Alice",
        "LastName": "Smith",
        "Email": "alice@owner.com",
        "Address": "456 Oak Ave",
        "DateOfBirth": "1992-05-15"
    },
    {
        "Id": "669ce1bf-fd1b-49e7-acd8-405513c7598a",
        "FirstName": "Sarah",
        "LastName": "Bistro",
        "Email": "sarah@owner.com",
        "Address": "789 Culinary Street",
        "DateOfBirth": "1982-11-30"
    },
    {
        "Id": "808f6636-8ed3-4df8-99e1-f06aef1f65de",
        "FirstName": "Mark",
        "LastName": "Taylor",
        "Email": "mark@customer.com",
        "Address": "789 Lake Blvd",
        "DateOfBirth": "1988-11-20"
    },
    {
        "Id": "bb43517b-4224-4936-906f-2b416159469b",
        "FirstName": "Emma",
        "LastName": "Brown",
        "Email": "emma@customer.com",
        "Address": "321 Pine St",
        "DateOfBirth": "1995-03-10"
    }
]